envrac/__init__.py
envrac/config.py
envrac/envrac.py
envrac/exceptions.py
envrac/parser.py
envrac/register.py
envrac/types.py
envrac/utils.py
envrac/varspec.py
tests/__init__.py
tests/conftest.py
tests/test_basic_reading.py
tests/test_consistency_checks.py
tests/test_dict_method.py
tests/test_misc.py
tests/type_mixins.py
envrac-0.0.2.dist-info/LICENSE
envrac-0.0.2.dist-info/METADATA
envrac-0.0.2.dist-info/WHEEL
envrac-0.0.2.dist-info/top_level.txt
envrac-0.0.2.dist-info/RECORD
