Metadata-Version: 2.1
Name: envrac
Version: 0.0.2
Summary: Brings consistency to environment variables
Author: Andrew Buchan
Author-email: Andrew Buchan <andyhasit@gmail.com>
Project-URL: Homepage, https://github.com/andyhasit/envrac
Project-URL: Issues, https://github.com/andyhasit/envrac/issues
Classifier: Programming Language :: Python :: 3
Classifier: License :: OSI Approved :: MIT License
Classifier: Operating System :: OS Independent
Requires-Python: >=3.8
License-File: LICENSE
